<?xml version = '1.0' encoding = 'UTF-8'?>
<Relation class="oracle.dbtools.crest.model.design.logical.Relation" name="Relation_19" directorySegmentName="seg_0" id="FAA332D1-FED4-50D9-B11B-F9EA3F8DE5C9">
<createdBy>paulo</createdBy>
<createdTime>2024-10-10 12:39:59 UTC</createdTime>
<ownerDesignName>seguradora</ownerDesignName>
<engineerTo>
<item key="A093F042-15DD-8A17-7848-FBFEAA7D3857" value="true"/>
</engineerTo>
<sourcePk>AD877044-D095-EB75-8D68-2FD0A63774A9</sourcePk>
<identifying>true</identifying>
<optionalSource>true</optionalSource>
<optionalTarget>false</optionalTarget>
<sourceCardinality>1</sourceCardinality>
<sourceEntity>38150AD1-1549-D5D4-EE13-D5C5174F898C</sourceEntity>
<targetCardinalityString>*</targetCardinalityString>
<targetEntity>A20BB86A-F05D-B95F-54B9-9921A648405A</targetEntity>
<transferable>true</transferable>
<deleteRule>NO ACTION</deleteRule>
</Relation>
